<layout id="TargetLayout">
  <drawable id="TargetLayoutDrawables"/>
  
  <label id="lblTargetRelBRG" text="RelBrg" x="121" y="91" font="Gfx.FONT_SMALL" justification="Gfx.TEXT_JUSTIFY_RIGHT" color="Gfx.COLOR_WHITE" />
  <label id="lblTargetBRG" text="Brg" x="121" y="161" font="Gfx.FONT_SMALL" justification="Gfx.TEXT_JUSTIFY_RIGHT" color="Gfx.COLOR_WHITE" />
  <label id="lblTargetKNT" text="Knt" x="137" y="91" font="Gfx.FONT_SMALL" justification="Gfx.TEXT_JUSTIFY_LEFT" color="Gfx.COLOR_WHITE" />
  <label id="lblTargetNM" text="nm" x="137" y="161" font="Gfx.FONT_SMALL" justification="Gfx.TEXT_JUSTIFY_LEFT" color="Gfx.COLOR_WHITE" />

  <label id="targetTime" text="" x="center" y="11" font="Gfx.FONT_LARGE" justification="Gfx.TEXT_JUSTIFY_CENTER" color="Gfx.COLOR_WHITE" />
  <label id="targetName" text="" x="center" y="189" justification="Gfx.TEXT_JUSTIFY_CENTER" font="Gfx.FONT_MEDIUM" color="Gfx.COLOR_WHITE" />
  <label id="targetRelBRG" text="" x="125" y="41" font="Gfx.FONT_NUMBER_MEDIUM" justification="Gfx.TEXT_JUSTIFY_RIGHT"  color="Gfx.COLOR_WHITE" />
  <label id="targetBrg" text="" x="125" y="112" font="Gfx.FONT_NUMBER_MEDIUM" justification="Gfx.TEXT_JUSTIFY_RIGHT"  color="Gfx.COLOR_WHITE" />
  <label id="targetKnt" text="" x="133" y="41" font="Gfx.FONT_NUMBER_MEDIUM" justification="Gfx.TEXT_JUSTIFY_LEFT"  color="Gfx.COLOR_WHITE" />
  <label id="targetNM" text="" x="133" y="112" font="Gfx.FONT_NUMBER_MEDIUM" justification="Gfx.TEXT_JUSTIFY_LEFT"  color="Gfx.COLOR_WHITE" />

  <label id="targetBadPos" text="" x="center" y="55" font="Gfx.FONT_LARGE" justification="Gfx.TEXT_JUSTIFY_CENTER"  color="Gfx.COLOR_RED" />


</layout>